pprp/__init__.py
pprp/adapters.py
pprp/config.py
pprp/crypto_2.py
pprp/crypto_3.py
pprp/pbkdf2_2.py
pprp/pbkdf2_3.py
pprp/sink.py
pprp/source.py
pprp/utility.py
pprp/resources/README.rst
pprp/resources/requirements.txt
pprp-0.2.5.dist-info/DESCRIPTION.rst
pprp-0.2.5.dist-info/METADATA
pprp-0.2.5.dist-info/metadata.json
pprp-0.2.5.dist-info/RECORD
pprp-0.2.5.dist-info/top_level.txt
pprp-0.2.5.dist-info/WHEEL
