Metadata-Version: 2.0
Name: pprp
Version: 0.2.5
Summary: A pure-Python Rijndael (AES) and PBKDF2 library. Python2.7- and Python3-compatible.
Home-page: https://github.com/dsoprea/RijndaelPbkdf
Author: Dustin Oprea
Author-email: myselfasunder@gmail.com
License: GPL 2
Keywords: rijdael pbkdf2
Platform: UNKNOWN
